Workbook

Sheet 📊 Resumen
A1: 🚛 VOLQUETA INTERNATIONAL 8900 — PANEL DE CONTROL
A3: ── INVERSIÓN INICIAL ──
A4: Compra de la volqueta | B4: 32000000
A5: Reparación y puesta a punto | B5: 31000000
A6: TOTAL INVERTIDO | B6: =B4+B5 -> 63000000
A8: ── MES ACTUAL ──
A9: Subtotal bruto de viajes | B9: ='💵 Ingresos'!F2 -> 1130000
A10: Total neto (después del conductor) | B10: ='💵 Ingresos'!F5 -> -103900
A11: Total gastos del mes | B11: ='💸 Gastos'!D2 -> 2510000
A12: Ganancia / Pérdida del mes | B12: =B10-B11 -> -2613900
A14: ── RECUPERACIÓN DE INVERSIÓN ──
A15: Total recuperado hasta hoy | B15: ='📈 Recuperación'!B3 -> -1380000
A16: Falta por recuperar | B16: ='📈 Recuperación'!B4 -> 64380000
A17: % recuperado | B17: ='📈 Recuperación'!B5 -> -0.021904762
A18: Falta por recuperar | B18: ='📈 Recuperación'!B4 -> 64380000
A19: % recuperado | B19: ='📈 Recuperación'!B5 -> -0.021904762

Sheet 💸 Gastos
A1: 💸 REGISTRO DE GASTOS
A2: TOTAL GASTOS DEL MES (incluye salario conductor) | D2: =D4+SUM(D5:D1000) -> 2510000
A3: Fecha | B3: Descripción del gasto | C3: Categoría | D3: Valor ($)
A4: Salario conductor (fijo — no borrar) | D4: 1200000
A5: 15/05/2025 | B5: Cambio de aceite motor | C5: Mantenimiento | D5: 180000
A6: 18/05/2025 | B6: Pastillas de freno | C6: Reparación | D6: 320000
A7: 20/05/2025 | B7: ACPM 80 galones | C7: Combustible | D7: 560000
A8: 22/05/2025 | B8: Revisión técnico-mecánica | C8: Documentos | D8: 250000

Sheet 💵 Ingresos
A1: 💵 REGISTRO DE VIAJES E INGRESOS
A2: Subtotal bruto (suma de todos los viajes) | F2: =SUM(D8:D1000) -> 1130000
A3: - Comisión conductor (3%) | F3: =F2*0.03 -> 33900
A4: - Salario conductor | F4: ='💸 Gastos'!D4 -> 1200000
A5: TOTAL NETO (lo que queda para ti) | F5: =F2-F3-F4 -> -103900
A6: Total viajes registrados este mes | F6: =COUNTIF(A8:A1000,"<>") -> 4
A7: Fecha | B7: Destino / Ruta | C7: Material cargado | D7: Valor ($) | E7: Peso (ton) | F7: Observaciones
A8: 02/05/2025 | B8: Cantera El Moral → Obra Av. 68 | C8: Asfalto | D8: 280000 | E8: 18
A9: 02/05/2025 | B9: Cantera El Moral → Obra Av. 68 | C9: Asfalto | D9: 280000 | E9: 18
A10: 05/05/2025 | B10: Planta → Vía Tunja | C10: Agregado triturado | D10: 320000 | E10: 20
A11: 08/05/2025 | B11: Planta → Sogamoso centro | C11: Gravilla | D11: 250000 | E11: 16 | F11: Viaje corto

Sheet 📈 Recuperación
A1: 📈 RECUPERACIÓN DE INVERSIÓN
A2: Total invertido | B2: ='📊 Resumen'!B6 -> 63000000
A3: Total recuperado | B3: =SUM(E8:E100) -> -1380000
A4: Falta por recuperar | B4: =B2-B3 -> 64380000
A5: % recuperado | B5: =IF(B2>0,B3/B2,0) -> -0.021904762
A7: Mes | B7: Ingresos | C7: Gastos | D7: Ganancia neta | E7: Ganancia acumulada
A8: Mayo 2025 | B8: 1130000 | C8: 2510000 | D8: =B8-C8 -> -1380000 | E8: =D8 -> -1380000
D9: =IF(B9="","",B9-C9) | E9: =IF(D9="","",E8+D9)
D10: =IF(B10="","",B10-C10) | E10: =IF(D10="","",E9+D10)
D11: =IF(B11="","",B11-C11) | E11: =IF(D11="","",E10+D11)
D12: =IF(B12="","",B12-C12) | E12: =IF(D12="","",E11+D12)
D13: =IF(B13="","",B13-C13) | E13: =IF(D13="","",E12+D13)
D14: =IF(B14="","",B14-C14) | E14: =IF(D14="","",E13+D14)
D15: =IF(B15="","",B15-C15) | E15: =IF(D15="","",E14+D15)
D16: =IF(B16="","",B16-C16) | E16: =IF(D16="","",E15+D16)
D17: =IF(B17="","",B17-C17) | E17: =IF(D17="","",E16+D17)
D18: =IF(B18="","",B18-C18) | E18: =IF(D18="","",E17+D18)
D19: =IF(B19="","",B19-C19) | E19: =IF(D19="","",E18+D19)
D20: =IF(B20="","",B20-C20) | E20: =IF(D20="","",E19+D20)
... D49: =IF(B49="","",B49-C49) | E49: =IF(D49="","",E48+D49)

Sheet 📋 Cómo usar
A1: 📋 CÓMO USAR ESTE ARCHIVO
A2: PESTAÑAS
A3: 📊 Resumen → Tu panel principal. Solo mira, no escribas aquí.
A4: 💸 Gastos → Registra cada gasto cuando ocurra.
A5: 💵 Ingresos → Registra los viajes a fin de mes con los recibos.
A6: 📈 Recuperación → Agrega una fila nueva cada mes.
A8: CÓMO REGISTRAR UN GASTO
A9: 1. Ve a la pestaña 💸 Gastos.
A10: 2. Agrega una fila nueva: fecha, descripción, categoría y valor.
A11: 3. El total se actualiza solo arriba.
A13: CÓMO REGISTRAR VIAJES (A FIN DE MES)
A14: 1. Recibe los recibos del conductor.
... A22: 4. El % de recuperación se actualiza solo.
